format_multiple_errors/__init__.py
format_multiple_errors/__main__.py
format_multiple_errors/formatter.py
format_multiple_errors/pandas.py
format_multiple_errors/typing.py
format_multiple_errors-0.0.3.dist-info/LICENSE
format_multiple_errors-0.0.3.dist-info/METADATA
format_multiple_errors-0.0.3.dist-info/WHEEL
format_multiple_errors-0.0.3.dist-info/entry_points.txt
format_multiple_errors-0.0.3.dist-info/top_level.txt
format_multiple_errors-0.0.3.dist-info/RECORD
