Metadata-Version: 2.1
Name: format_multiple_errors
Version: 0.0.3
Summary: A small widget to be able to format multiple, asymmetric errors easily.
Author-email: Ed Bennett <e.j.bennett@swansea.ac.uk>
Project-URL: Homepage, https://github.com/edbennett/format_multiple_errors
Project-URL: Bug Tracker, https://github.com/edbennett/format_multiple_errors/issues
Classifier: Programming Language :: Python :: 3
Classifier: License :: OSI Approved :: MIT License
Classifier: Operating System :: OS Independent
Requires-Python: >=3.9
License-File: LICENSE
Provides-Extra: tables
Requires-Dist: pandas; extra == "tables"
Requires-Dist: jinja2; extra == "tables"
